ezmodulemanager/__init__.py
ezmodulemanager/exceptions.py
ezmodulemanager/libutils.py
ezmodulemanager/module_manager.py
ezmodulemanager/registry.py
ezmodulemanager-1.0.1.dist-info/METADATA
ezmodulemanager-1.0.1.dist-info/WHEEL
ezmodulemanager-1.0.1.dist-info/licenses/LICENSE
ezmodulemanager-1.0.1.dist-info/RECORD
