Metadata-Version: 2.4
Name: ezmodulemanager
Version: 1.0.1
Summary: Lightweight Framework - Remove circular dependencies in an event-driven way by decoupling your imports from your class/function execution.
Project-URL: Documentation, https://github.com/Obsidian-Cloud/EZModuleManager/blob/main/README.md
Project-URL: GitHub, https://github.com/Obsidian-Cloud/EZModuleManager
Project-URL: Issues, https://github.com/Obsidian-Cloud/EZModuleManager/issues
Author-email: Obsidian-Cloud <obsidiancloud25@gmail.com>
License-Expression: MIT
License-File: LICENSE
Keywords: decouple,framework,imports,index,loader,manager,module,module manager,packaging,plugin,registry
Classifier: Development Status :: 5 - Production/Stable
Classifier: Intended Audience :: Developers
Classifier: License :: OSI Approved :: MIT License
Classifier: Operating System :: OS Independent
Classifier: Programming Language :: Python :: 3
Classifier: Programming Language :: Python :: 3.8
Classifier: Programming Language :: Python :: 3.9
Classifier: Programming Language :: Python :: 3.10
Classifier: Programming Language :: Python :: 3.11
Classifier: Programming Language :: Python :: 3.12
Classifier: Programming Language :: Python :: 3.13
Classifier: Programming Language :: Python :: 3.14
Classifier: Topic :: Software Development :: Build Tools
Classifier: Topic :: Software Development :: Libraries
Classifier: Topic :: System :: Software Distribution
Requires-Python: >=3.8
